pybatsim/__init__.py
pybatsim/batsim/__init__.py
pybatsim/batsim/batsim.py
pybatsim/batsim/cmds/__init__.py
pybatsim/batsim/cmds/experiments.py
pybatsim/batsim/cmds/launcher.py
pybatsim/batsim/network.py
pybatsim/batsim/storageController.py
pybatsim/batsim/tools/__init__.py
pybatsim/batsim/tools/experiments.py
pybatsim/batsim/tools/launcher.py
pybatsim/cmdline.py
pybatsim/plugin.py
pybatsim/schedulers/__init__.py
pybatsim/schedulers/easyBackfill.py
pybatsim/schedulers/fcfsSchedSleep.py
pybatsim/schedulers/fillerSched.py
pybatsim/schedulers/fillerSchedWithEvents.py
pybatsim/schedulers/intervalContainer.py
pybatsim/schedulers/randomSched.py
pybatsim/schedulers/schedBebida.py
pybatsim/schedulers/unMaintained/common_pyss_adaptator.py
pybatsim/schedulers/unMaintained/easyBackfillNotopo.py
pybatsim/schedulers/unMaintained/easyEnergyBudget.py
pybatsim/schedulers/unMaintained/easySjbfBackfillNotopo.py
pybatsim-4.0.0a0.dist-info/entry_points.txt
pybatsim-4.0.0a0.dist-info/LICENSE
pybatsim-4.0.0a0.dist-info/WHEEL
pybatsim-4.0.0a0.dist-info/METADATA
pybatsim-4.0.0a0.dist-info/RECORD
