Metadata-Version: 2.1
Name: pybatsim
Version: 4.0.0a0
Summary: Python API and schedulers for Batsim
Home-page: https://gitlab.inria.fr/batsim/pybatsim
License: LGPL-3.0-only
Keywords: scheduler,simulation
Author: Henri Casanova
Author-email: henric@hawaii.edu
Maintainer: Raphaël Bleuse
Maintainer-email: raphael.bleuse@inria.fr
Requires-Python: >=3.7.1,<4.0.0
Classifier: Development Status :: 4 - Beta
Classifier: Environment :: Console
Classifier: Intended Audience :: Developers
Classifier: Intended Audience :: Science/Research
Classifier: License :: OSI Approved :: GNU Lesser General Public License v3 (LGPLv3)
Classifier: Programming Language :: Python :: 3
Classifier: Programming Language :: Python :: 3.10
Classifier: Programming Language :: Python :: 3.8
Classifier: Programming Language :: Python :: 3.9
Classifier: Topic :: Scientific/Engineering
Classifier: Topic :: System :: Distributed Computing
Requires-Dist: docopt (>=0.6.2,<0.7.0)
Requires-Dist: importlib-metadata (>=3.6); python_version < "3.10"
Requires-Dist: procset (>=1.0,<2.0)
Requires-Dist: pyzmq (>=22.0.3,<23.0.0)
Requires-Dist: sortedcontainers (>=2.3.0,<3.0.0)
Project-URL: Repository, https://gitlab.inria.fr/batsim/pybatsim
